elsai_agent_hub/__init__.py
elsai_agent_hub/agent_workflow/__init__.py
elsai_agent_hub/agent_workflow/sales_agent.py
elsai_agent_hub/micro_agent/__init__.py
elsai_agent_hub/micro_agent/content_generate.py
elsai_agent_hub/micro_agent/vector_db/__init__.py
elsai_agent_hub/micro_agent/vector_db/chroma_db.py
elsai_agent_hub/micro_agent/vector_db/pinecone_db.py
elsai_agent_hub/model/__init__.py
elsai_agent_hub/model/model.py
elsai_agent_hub/tests/__init__.py
elsai_agent_hub/tests/test_chroma_db.py
elsai_agent_hub/tests/test_content_generate.py
elsai_agent_hub/tests/test_email_sender.py
elsai_agent_hub/tests/test_pdf_reader.py
elsai_agent_hub/tests/test_pinecone_db.py
elsai_agent_hub/tests/test_web_scrap.py
elsai_agent_hub/tools/__init__.py
elsai_agent_hub/tools/email_sender.py
elsai_agent_hub/tools/read_document.py
elsai_agent_hub/tools/web_scrap.py
elsai_agent_hub/utils/__init__.py
elsai_agent_hub/utils/log.py
elsai_agent_hub/utils/text_utils.py
elsai_agent_hub/utils/utils.py
elsai_agent_hub-0.0.3.dist-info/AUTHORS.md
elsai_agent_hub-0.0.3.dist-info/LICENSE
elsai_agent_hub-0.0.3.dist-info/METADATA
elsai_agent_hub-0.0.3.dist-info/WHEEL
elsai_agent_hub-0.0.3.dist-info/top_level.txt
elsai_agent_hub-0.0.3.dist-info/RECORD
