Metadata-Version: 2.1
Name: elsai-agent-hub
Version: 0.0.3
Summary: A Python package designed to facilitate the quick and customized development of agent-driven applications leveraging large language models (LLMs). This library aims to streamline tasks such as analyzing customer data, sending emails, and extracting information from various sources, including PDFs and web URLs.
Author: Sriramraja.K
Author-email: sriramraja.k@optisolbusiness.com
License: MIT
Classifier: Development Status :: 3 - Alpha
Classifier: Intended Audience :: Developers
Classifier: License :: OSI Approved :: MIT License
Classifier: Programming Language :: Python :: 3.8
Classifier: Programming Language :: Python :: 3.9
Classifier: Programming Language :: Python :: 3.10
Classifier: Programming Language :: Python :: 3.11
Requires-Python: >=3.8.1, <3.12
License-File: LICENSE
License-File: AUTHORS.md
Requires-Dist: PyMuPDF ==1.24.7
Requires-Dist: beautifulsoup4 ==4.12.3
Requires-Dist: chromadb ==0.5.4
Requires-Dist: duckduckgo-search ==6.1.9
Requires-Dist: langchain-community ==0.2.6
Requires-Dist: langchain-openai ==0.1.13
Requires-Dist: pandas ==2.2.2
Requires-Dist: pinecone-client[grpc] ==4.1.2
Requires-Dist: python-docx ==1.1.2
Requires-Dist: python-dotenv ==1.0.1
Requires-Dist: tqdm ==4.66.4
